{
  "mode": "pre",
  "tag": "alpha",
  "initialVersions": {
    "gqless": "0.0.1-alpha.23",
    "@gqless/cli": "0.0.1-alpha.23",
    "@gqless/logger": "0.0.1-alpha.23",
    "@gqless/react": "0.0.1-alpha.23",
    "@gqless/schema": "0.0.1-alpha.23",
    "@gqless/utils": "0.0.1-alpha.23",
    "react-github": "0.0.1-alpha.26",
    "react-hackernews": "0.0.1-alpha.26",
    "gqless-example": "0.0.1-alpha.26",
    "@internal/fixtures": "0.0.1-alpha.22",
    "@internal/website": "0.0.1-alpha.22",
    "babel-plugin-gqless": "0.0.1-alpha.27",
    "@gqless/devtools": "0.0.1-alpha.27",
    "example": "0.0.1-alpha.22",
    "gqlhub": "1.0.0"
  },
  "changesets": [
    "giant-horses-complain",
    "gold-baboons-kneel",
    "grumpy-kiwis-lick",
    "itchy-trees-refuse",
    "many-boxes-fail",
    "nasty-zebras-count",
    "odd-parents-destroy",
    "smart-taxis-tan",
    "tame-cooks-film",
    "tender-wasps-cheer",
    "wild-cars-beam"
  ]
}
